streammachine_driver-1.0.0-py3.8-nspkg.pth
streammachine/driver/__init__.py
streammachine/driver/client/__init__.py
streammachine/driver/client/auth.py
streammachine/driver/client/client.py
streammachine/driver/client/receiver.py
streammachine/driver/client/sender.py
streammachine/driver/client/syncsender.py
streammachine/driver/domain/__init__.py
streammachine/driver/domain/base.py
streammachine/driver/domain/config.py
streammachine/driver/domain/domain.py
streammachine/driver/serializer/__init__.py
streammachine/driver/serializer/provider.py
streammachine/driver/serializer/serializers.py
streammachine/driver/serializer/type.py
streammachine/driver/util/__init__.py
streammachine_driver-1.0.0.dist-info/AUTHORS
streammachine_driver-1.0.0.dist-info/METADATA
streammachine_driver-1.0.0.dist-info/WHEEL
streammachine_driver-1.0.0.dist-info/namespace_packages.txt
streammachine_driver-1.0.0.dist-info/top_level.txt
streammachine_driver-1.0.0.dist-info/RECORD
